somfy_protect_api/__init__.py
somfy_protect_api/api/__init__.py
somfy_protect_api/api/log.py
somfy_protect_api/api/model.py
somfy_protect_api/api/somfy_protect_api.py
somfy_protect_api/api/devices/__init__.py
somfy_protect_api/api/devices/base.py
somfy_protect_api/api/devices/category.py
somfy_protect_api/api/devices/extender.py
somfy_protect_api/api/devices/indoor_camera.py
somfy_protect_api/api/devices/indoor_siren.py
somfy_protect_api/api/devices/infrared_sensor.py
somfy_protect_api/api/devices/intellitag.py
somfy_protect_api/api/devices/key_fob.py
somfy_protect_api/api/devices/link.py
somfy_protect_api/api/devices/myfox_camera.py
somfy_protect_api/api/devices/outdoor_camera.py
somfy_protect_api/api/devices/outdoor_siren.py
somfy_protect_api/api/devices/smoke_detector.py
somfy_protect_api-0.1.8.dist-info/LICENSE
somfy_protect_api-0.1.8.dist-info/METADATA
somfy_protect_api-0.1.8.dist-info/WHEEL
somfy_protect_api-0.1.8.dist-info/top_level.txt
somfy_protect_api-0.1.8.dist-info/RECORD
