Metadata-Version: 2.1
Name: somfy-protect-api
Version: 0.1.8
Summary: Python3 API Client for Somfy Protect (Home Alarm)
Home-page: https://github.com/Minims/somfy-protect-api
Author: Minims
Author-email: github@minims.fr
License: GNU General Public License v3.0
Platform: UNKNOWN
Requires-Python: >=3.6.1,<4.0
License-File: LICENSE
Requires-Dist: requests-oauthlib (<2.0.0,>=1.3.0)
Requires-Dist: aenum (>=3.1.0)
